myles_test_project_slug/__init__.py
myles_test_project_slug/myles_test_project_slug.py
myles_test_project_slug-0.1.0.dist-info/DESCRIPTION.rst
myles_test_project_slug-0.1.0.dist-info/METADATA
myles_test_project_slug-0.1.0.dist-info/RECORD
myles_test_project_slug-0.1.0.dist-info/WHEEL
myles_test_project_slug-0.1.0.dist-info/metadata.json
myles_test_project_slug-0.1.0.dist-info/top_level.txt
