Metadata-Version: 2.0
Name: myles-test-project-slug
Version: 0.1.0
Summary: Myles test project contains all the test project code yI need to make a test project.
Home-page: https://github.com/myles1/myles_test_project_slug
Author: Myles Hollowed
Author-email: mylesthollowed@gmail.com
License: MIT license
Keywords: myles_test_project_slug
Platform: UNKNOWN
Classifier: Development Status :: 2 - Pre-Alpha
Classifier: Intended Audience :: Developers
Classifier: License :: OSI Approved :: MIT License
Classifier: Natural Language :: English
Classifier: Programming Language :: Python :: 2
Classifier: Programming Language :: Python :: 2.6
Classifier: Programming Language :: Python :: 2.7
Classifier: Programming Language :: Python :: 3
Classifier: Programming Language :: Python :: 3.3
Classifier: Programming Language :: Python :: 3.4
Classifier: Programming Language :: Python :: 3.5
